[{"name": "Underground Pizza", "link": "/biz/underground-pizza-baltimore-2?osq=pizza", "review_counts": 414}, {"name": "Isabella\u2019s Brick Oven Pizza and Panini", "link": "/biz/isabellas-brick-oven-pizza-and-panini-baltimore?osq=pizza", "review_counts": 591}, {"name": "Angeli\u2019s Pizzeria", "link": "/biz/angelis-pizzeria-baltimore-2?osq=pizza", "review_counts": 418}, {"name": "BricknFire at Baltimore Marriott Inner Harbor at Camden Yards", "link": "/biz/bricknfire-at-baltimore-marriott-inner-harbor-at-camden-yards-baltimore?osq=pizza", "review_counts": 256}, {"name": "HomeSlyce - Mt. Vernon", "link": "/biz/homeslyce-mt-vernon-baltimore-3?osq=pizza", "review_counts": 492}, {"name": "Tre Fratelli Italian Ristorante", "link": "/biz/tre-fratelli-italian-ristorante-baltimore?osq=pizza", "review_counts": 28}, {"name": "Paulie Gee\u2019s Hampden", "link": "/biz/paulie-gees-hampden-baltimore-3?osq=pizza", "review_counts": 397}, {"name": "Little Donna\u2019s", "link": "/biz/little-donna-s-baltimore?osq=pizza", "review_counts": 76}, {"name": "Matthew\u2019s Pizza", "link": "/biz/matthews-pizza-baltimore?osq=pizza", "review_counts": 565}, {"name": "Di Pasquale\u2019s Marketplace", "link": "/biz/di-pasquales-marketplace-baltimore?osq=pizza", "review_counts": 514}]